docpipe/__init__.py
docpipe/__main__.py
docpipe/__version__.py
docpipe/_memory.py
docpipe/_protocols.py
docpipe/_types.py
docpipe/_version.py
docpipe/pipeline.py
docpipe/cli/__init__.py
docpipe/cli/_typer.py
docpipe/formatters/_rag_jsonl.py
docpipe/loaders/__init__.py
docpipe/loaders/_docx.py
docpipe/loaders/_pdfium.py
docpipe/loaders/_pymupdf.py
docpipe/loaders/_xlsx.py
docpipe/loaders/pdf.py
docpipe/loaders/pymupdf_serializer.py
docpipe/utils/_table_parser.py
docpipe_mini-0.2.3.dist-info/METADATA
docpipe_mini-0.2.3.dist-info/WHEEL
docpipe_mini-0.2.3.dist-info/entry_points.txt
docpipe_mini-0.2.3.dist-info/RECORD
