Metadata-Version: 2.4
Name: docpipe-mini
Version: 0.2.3
Summary: Minimal document-to-jsonl serializer with coordinates for AI
Project-URL: Homepage, https://github.com/docpipe/docpipe-mini
Project-URL: Repository, https://github.com/docpipe/docpipe-mini
Project-URL: Documentation, https://docpipe-mini.readthedocs.io
Project-URL: Issues, https://github.com/docpipe/docpipe-mini/issues
Author-email: DocPipe Team <team@docpipe.ai>
License: MIT
Keywords: ai,coordinates,document,jsonl,pdf,serialization
Classifier: Development Status :: 3 - Alpha
Classifier: Intended Audience :: Developers
Classifier: License :: OSI Approved :: MIT License
Classifier: Programming Language :: Python :: 3
Classifier: Programming Language :: Python :: 3.11
Classifier: Programming Language :: Python :: 3.12
Classifier: Topic :: Scientific/Engineering :: Information Analysis
Classifier: Topic :: Software Development :: Libraries :: Python Modules
Classifier: Topic :: Text Processing
Requires-Python: >=3.11
Requires-Dist: typing-extensions>=4.0.0
Provides-Extra: all
Requires-Dist: mypy>=1.8.0; extra == 'all'
Requires-Dist: openpyxl>=3.1.0; extra == 'all'
Requires-Dist: pillow>=10.0.0; extra == 'all'
Requires-Dist: pypdfium2>=4.18.0; extra == 'all'
Requires-Dist: pytest-benchmark>=4.0.0; extra == 'all'
Requires-Dist: pytest>=8.0.0; extra == 'all'
Requires-Dist: python-docx>=0.8.11; extra == 'all'
Requires-Dist: rich>=13.0.0; extra == 'all'
Requires-Dist: ruff>=0.1.0; extra == 'all'
Requires-Dist: typer>=0.9.0; extra == 'all'
Requires-Dist: types-pyyaml>=6.0.0; extra == 'all'
Provides-Extra: cli
Requires-Dist: rich>=13.0.0; extra == 'cli'
Requires-Dist: typer>=0.9.0; extra == 'cli'
Provides-Extra: dev
Requires-Dist: mypy>=1.8.0; extra == 'dev'
Requires-Dist: pypdfium2>=4.18.0; extra == 'dev'
Requires-Dist: pytest-benchmark>=4.0.0; extra == 'dev'
Requires-Dist: pytest>=8.0.0; extra == 'dev'
Requires-Dist: rich>=13.0.0; extra == 'dev'
Requires-Dist: ruff>=0.1.0; extra == 'dev'
Requires-Dist: typer>=0.9.0; extra == 'dev'
Requires-Dist: types-pyyaml>=6.0.0; extra == 'dev'
Provides-Extra: docx
Requires-Dist: python-docx>=0.8.11; extra == 'docx'
Provides-Extra: full
Requires-Dist: openpyxl>=3.1.0; extra == 'full'
Requires-Dist: pillow>=10.0.0; extra == 'full'
Requires-Dist: pymupdf>=1.23.0; extra == 'full'
Requires-Dist: python-docx>=0.8.11; extra == 'full'
Requires-Dist: rich>=13.0.0; extra == 'full'
Requires-Dist: typer>=0.9.0; extra == 'full'
Provides-Extra: image
Requires-Dist: pillow>=10.0.0; extra == 'image'
Provides-Extra: pdf
Requires-Dist: pypdfium2>=4.18.0; extra == 'pdf'
Provides-Extra: pdf-fast
Requires-Dist: pymupdf>=1.23.0; extra == 'pdf-fast'
Provides-Extra: xlsx
Requires-Dist: openpyxl>=3.1.0; extra == 'xlsx'
